compose_flow
tests
