Metadata-Version: 2.1
Name: compose-flow
Version: 3.7.1
Summary: codified workflows for docker compose
Home-page: https://github.com/openslate/compose-flow
Author: OpenSlate
Author-email: code@openslate.com
License: UNKNOWN
Platform: UNKNOWN
